<document
  xmlns="http://maven.apache.org/changes/1.0.0"
  xmlns:xsi="http://www.w3.org/2001/XMLSchema-instance"
  xsi:schemaLocation="http://maven.apache.org/changes/1.0.0 http://maven.apache.org/xsd/changes-1.0.0.xsd">
  <body>
    <release
      version="5.5"
      description="TBD"
      date="TBA">
    </release>
    <release
      version="5.4"
      description="plugins and versioning"
      date="2020-03-14">
      <action type="update">
        Rework pom to use plugin management always. 
      </action>
      <action type="add">
        Add more plugins with versions. 
      </action>
    </release>
    <release
      version="5.3"
      description="less maven properties"
      date="2018-12-28">
      <action type="update">
        Rework pom to use more version properties. Upgrade to current plugin versions.
      </action>
      <action type="add">
        Datenschutzerklärung
      </action>
    </release>
    <release
      version="5.2"
      description="less maven properties"
      date="2017-05-10">
      <action type="update">
        Rework pom to use less maven properties
      </action>
      <action type="update">
        Remove eclipse artifacts from scm
      </action>
    </release>
    <release
      version="5.1"
      description="pom and reports"
      date="2017-04-13">
      <action type="update">
        Go back to site plugin 3.4 since 3.6 causes failures.
      </action>
    </release>
    <release
      version="5.0"
      description="pom and reports"
      date="2017-03-20">
      <action type="add">
        Add and update towards maven central.
      </action>
      <action type="update">
        Update plugin and plugin management versions.
      </action>
      <action type="add">
        Add changes report.
      </action>
      <action type="add">
        Add taglist report.
      </action>
      <action type="update">
        Removed version properties in favor of more reports for the site.
      </action>
    </release>
  </body>
</document>